{
  "m_Shader": {
    "m_FileID": 1,
    "m_PathID": 4301164663291589078,
    "Name": "Hidden/m_lob_PlayerPBRLengcy_lv3",
    "IsNull": false
  },
  "m_SavedProperties": {
    "m_TexEnvs": {
      "_BumpMapNr": {
        "m_Texture": {
          "m_FileID": 3,
          "m_PathID": 2365725399246376914,
          "Name": "t_nm_lob_40340hand_lv3",
          "IsNull": false
        },
        "m_Scale": {
          "X": 1.0,
          "Y": 1.0
        },
        "m_Offset": {
          "X": 0.0,
          "Y": 0.0
        }
      },
      "_MainTex": {
        "m_Texture": {
          "m_FileID": 3,
          "m_PathID": 4544649024023807662,
          "Name": "t_d_lob_40340hand_lv3",
          "IsNull": false
        },
        "m_Scale": {
          "X": 1.0,
          "Y": 1.0
        },
        "m_Offset": {
          "X": 0.0,
          "Y": 0.0
        }
      },
      "_OutlineMap": {
        "m_Texture": {
          "m_FileID": 3,
          "m_PathID": -5542322617113004688,
          "Name": "t_i_lob_40340hand_lv1",
          "IsNull": false
        },
        "m_Scale": {
          "X": 1.0,
          "Y": 1.0
        },
        "m_Offset": {
          "X": 0.0,
          "Y": 0.0
        }
      }
    },
    "m_Ints": null,
    "m_Floats": {
      "_ActorScaleAttribute": 1.0,
      "_AlphaToMask": 0.0,
      "_AtVector": 0.0,
      "_BlendMode": 0.0,
      "_BlendOp": 0.0,
      "_BlendOpAlpha": 0.0,
      "_Cull": 0.0,
      "_Cutoff": 0.5,
      "_Debug": 0.0,
      "_DstBlendFactor": 10.0,
      "_DstBlendFactorAlpha": 10.0,
      "_FarWidth": 0.5,
      "_MainlightAttenuation": 0.04,
      "_MetallicOffset": 0.0,
      "_NearWidth": 0.5,
      "_NormalScale": 1.0,
      "_Offset": -5.0,
      "_OutlineWidth": 0.009,
      "_QueueOffset": 0.0,
      "_ReceiveShadows": 1.0,
      "_RenderType": 0.0,
      "_RoughNessOffset": 0.0,
      "_SHScale": 1.0,
      "_SHType": 1.0,
      "_ShadowOffset": 0.0,
      "_ShadowPow": 1.0,
      "_ShadowScale": 0.0,
      "_SrcBlendFactor": 5.0,
      "_SrcBlendFactorAlpha": 5.0,
      "_StencilComp": 8.0,
      "_StencilData": 0.0,
      "_StencilFailOp": 0.0,
      "_StencilPassOp": 0.0,
      "_StencilReadMask": 255.0,
      "_StencilWriteMask": 255.0,
      "_StencilZFailOp": 0.0,
      "_VCOLOR2N": 0.0,
      "_VTEX": 1.0,
      "_ZTest": 4.0,
      "_ZWrite": 1.0,
      "_actorscale": 1.0
    },
    "m_Colors": {
      "_OutlineColor": {
        "r": 0.5,
        "g": 0.5,
        "b": 0.5,
        "a": 1.0
      },
      "_SHBotColor": {
        "r": 3.3376963,
        "g": 3.3376963,
        "b": 3.3376963,
        "a": 1.0
      },
      "_SHTopColor": {
        "r": 2.7709177,
        "g": 2.7709177,
        "b": 2.7709177,
        "a": 1.0
      },
      "_SpecularColor": {
        "r": 1.0,
        "g": 1.0,
        "b": 1.0,
        "a": 1.0
      },
      "_lightDir": {
        "r": 9.48,
        "g": 3.68,
        "b": 0.0,
        "a": 0.0
      }
    }
  },
  "m_Name": "mat_lob_40340hand_lv3",
  "Name": "mat_lob_40340hand_lv3"
}